pycomposer/__init__.py
pycomposer/annotation.py
pycomposer/composer.py
pycomposer/dag.py
pycomposer/split_types.py
pycomposer/unevaluated.py
pycomposer/vm/__init__.py
pycomposer/vm/driver.py
pycomposer/vm/instruction.py
pycomposer/vm/program.py
pycomposer/vm/vm.py
sas-0.0.1.dist-info/METADATA
sas-0.0.1.dist-info/WHEEL
sas-0.0.1.dist-info/top_level.txt
sas-0.0.1.dist-info/RECORD
