Metadata-Version: 2.1
Name: sas
Version: 0.0.1
Summary: Python split annotations library
Home-page: https://www.github.com/weld-project/split-annotations
Author: Shoumik Palkar
Author-email: shoumik@cs.stanford.edu
License: UNKNOWN
Platform: UNKNOWN
Requires-Python: >=3.6
